CHANGELOG.rst
MANIFEST.in
README.rst
setup.py
tox.ini
remote_server/__init__.py
remote_server/authentication.py
remote_server/error.py
remote_server/exceptions.py
remote_server/router.py
remote_server/cache/__init__.py
remote_server/cache/redis.py
remote_server/tests/__init__.py
remote_server/tests/functional_tests.py
remote_worker.egg-info/PKG-INFO
remote_worker.egg-info/SOURCES.txt
remote_worker.egg-info/dependency_links.txt
remote_worker.egg-info/entry_points.txt
remote_worker.egg-info/not-zip-safe
remote_worker.egg-info/requires.txt
remote_worker.egg-info/top_level.txt