Metadata-Version: 1.1
Name: remote-worker
Version: 0.1.0
Summary: Gecko Cloud Remote Worker
Home-page: https://github.com/mozilla-services/remote-worker-server
Author: Mozilla Services
Author-email: services-dev@mozilla.com
License: UNKNOWN
Keywords: web services
Platform: UNKNOWN
Classifier: Programming Language :: Python
Classifier: Programming Language :: Python :: 3 :: Only
Classifier: Topic :: Internet :: WWW/HTTP
